{"players":[{"name":"Colly45x","platform":"xbox","division":"1","toPar":"-13","putt":"","hole":"","hio":"","albatross":"","seasonPts":565,"history":["-8","-5","-7","-14","-1"],"wins":3,"events":5,"prevRank":2,"pointsHistory":[100,80,100,125,160]},{"name":"Mr Longpole","platform":"xbox","division":"1","toPar":"-5","putt":"","hole":"14.4","hio":"","albatross":"","seasonPts":470,"history":["+3","-7","-1","-7","-4"],"wins":0,"events":5,"prevRank":4,"pointsHistory":[60,90,70,70,180]},{"name":"Er114ic","platform":"playstation","division":"1","toPar":"-1","putt":"","hole":"","hio":"","albatross":"","seasonPts":0,"history":[],"wins":0,"events":0,"prevRank":null},{"name":"Tenbobnote","platform":"playstation","division":"1","toPar":"E","putt":"","hole":"","hio":"","albatross":"","seasonPts":490,"history":["E","-","-4","-10","-6"],"wins":1,"events":4,"prevRank":3,"pointsHistory":[95,0,115,80,200]},{"name":"x3offthetee","platform":"xbox","division":"1","toPar":"E","putt":"","hole":"","hio":"","albatross":"","seasonPts":570,"history":["-2","-11","+5","-1","+4"],"wins":1,"events":5,"prevRank":1,"pointsHistory":[105,125,50,50,240]},{"name":"NoWorries37908","platform":"xbox","division":"1","toPar":"+16","putt":"26.5","hole":"","hio":"","albatross":"","seasonPts":0,"history":[],"wins":0,"events":0,"prevRank":null},{"name":"Horusphoenix","platform":"xbox","division":"2","toPar":"-16","putt":"46.6","hole":"","hio":"","albatross":"","seasonPts":290,"history":["-","-","-","-8","-4"],"wins":1,"events":2,"prevRank":6,"pointsHistory":[0,0,0,90,200]},{"name":"Hoplinkz","platform":"playstation","division":"2","toPar":"-6","putt":"","hole":"","hio":"","albatross":"","seasonPts":405,"history":["+2","+14","-","+3","+3"],"wins":0,"events":4,"prevRank":4,"pointsHistory":[80,70,0,95,160]},{"name":"Keep_of_Kalessin","platform":"playstation","division":"2","toPar":"-2","putt":"","hole":"17.0","hio":"","albatross":"","seasonPts":0,"history":[],"wins":0,"events":0,"prevRank":null},{"name":"Geordieboy85","platform":"playstation","division":"2","toPar":"+5","putt":"","hole":"","hio":"","albatross":"","seasonPts":0,"history":[],"wins":0,"events":0,"prevRank":null},{"name":"WingisBack","platform":"playstation","division":"2","toPar":"","putt":"","hole":"","hio":"","albatross":"","seasonPts":0,"history":[],"wins":0,"events":0,"prevRank":null},{"name":"SimChars68","platform":"steam","division":"2","toPar":"","putt":"","hole":"","hio":"","albatross":"","seasonPts":0,"history":[],"wins":0,"events":0,"prevRank":null},{"name":"Polekatt","platform":"steam","division":"3","toPar":"+13","putt":"15.8","hole":"","hio":"","albatross":"","seasonPts":0,"history":[],"wins":0,"events":0,"prevRank":null},{"name":"StandoCuz","platform":"xbox","division":"3","toPar":"","putt":"","hole":"","hio":"","albatross":"","seasonPts":180,"history":["-","-3","-10","-","-"],"wins":1,"events":2,"prevRank":3,"pointsHistory":[0,80,100,0,0]},{"name":"zdubz92","platform":"playstation","division":"3","toPar":"","putt":"","hole":"","hio":"","albatross":"","seasonPts":150,"history":["+7","+5","-","-","-"],"wins":0,"events":2,"prevRank":5,"pointsHistory":[80,70,0,0,0]},{"name":"GovernmentAgent","platform":"steam","division":"3","toPar":"","putt":"","hole":"","hio":"","albatross":"","seasonPts":180,"history":["+17","+14","-","-","-"],"wins":0,"events":2,"prevRank":4,"pointsHistory":[95,85,0,0,0]},{"name":"Bfctino","platform":"playstation","division":"3","toPar":"","putt":"","hole":"","hio":"","albatross":"","seasonPts":60,"history":["+22","-","-","-","-"],"wins":0,"events":1,"prevRank":6,"pointsHistory":[60,0,0,0,0]},{"name":"BotClappintonll","platform":"playstation","division":"3","toPar":"","putt":"","hole":"","hio":"","albatross":"","seasonPts":50,"history":["+35","-","-","-","-"],"wins":0,"events":1,"prevRank":7,"pointsHistory":[50,0,0,0,0]}],"par":"72","venue":"Foxwarren Manor & Mere GC","season":"5","week":"6","isSignature":true,"isDoubleBonus":false}